sympad/__init__.py
sympad/__main__.py
sympad/sympad.py
sympad-1.1.6.data/scripts/sympad
sympad-1.1.6.dist-info/LICENSE
sympad-1.1.6.dist-info/METADATA
sympad-1.1.6.dist-info/WHEEL
sympad-1.1.6.dist-info/top_level.txt
sympad-1.1.6.dist-info/RECORD
