Metadata-Version: 2.1
Name: sympad
Version: 1.1.6
Summary: Graphical symbolic math calculator / scratchpad using SymPy
Home-page: https://github.com/Pristine-Cat/sympad
Author: Tomasz Pytel
Author-email: tom_pytel@yahoo.com
License: BSD
Keywords: Math CAS SymPy GUI
Platform: UNKNOWN
Classifier: Intended Audience :: Education
Classifier: Intended Audience :: Science/Research
Classifier: License :: OSI Approved :: BSD License
Classifier: Operating System :: OS Independent
Classifier: Programming Language :: Python
Classifier: Programming Language :: Python :: 3
Classifier: Programming Language :: Python :: 3 :: Only
Classifier: Topic :: Scientific/Engineering
Classifier: Topic :: Scientific/Engineering :: Mathematics
Requires-Python: >=3.6
Requires-Dist: sympy (>=1.7.1)
